flask_mistune.py
setup.py
Flask_Mistune.egg-info/PKG-INFO
Flask_Mistune.egg-info/SOURCES.txt
Flask_Mistune.egg-info/dependency_links.txt
Flask_Mistune.egg-info/not-zip-safe
Flask_Mistune.egg-info/requires.txt
Flask_Mistune.egg-info/top_level.txt