Metadata-Version: 1.1
Name: Flask-Mistune
Version: 0.1.1
Summary: A interface between the Flask web framework and the Mistune Markdown parser.
Home-page: https://github.com/ellisonleao/flask-mistune/
Author: Ellison Leão
Author-email: ellisonleao@gmail.com
License: MIT
Platform: UNKNOWN
Classifier: Development Status :: 3 - Alpha
Classifier: Environment :: Web Environment
Classifier: Intended Audience :: Developers
Classifier: License :: OSI Approved :: MIT License
Classifier: Programming Language :: Python
Classifier: Topic :: Software Development :: Libraries :: Python Modules
